cnspy_ranging_evaluation/AssociateRanges.py
cnspy_ranging_evaluation/CSV_StaticBiasAnalysis.py
cnspy_ranging_evaluation/IMU_ROSbag2CSV.py
cnspy_ranging_evaluation/PlotTwoWayRanges.py
cnspy_ranging_evaluation/ROSBag_Pose2Ranges.py
cnspy_ranging_evaluation/ROSBag_TrueRanges.py
cnspy_ranging_evaluation/RangeEvaluation.py
cnspy_ranging_evaluation/RangeEvaluationTool.py
cnspy_ranging_evaluation/TWR_ROSbag2CSV.py
cnspy_ranging_evaluation/__init__.py
test/__init__.py
test/example.py
cnspy_ranging_evaluation-0.2.14.dist-info/LICENSE
cnspy_ranging_evaluation-0.2.14.dist-info/METADATA
cnspy_ranging_evaluation-0.2.14.dist-info/WHEEL
cnspy_ranging_evaluation-0.2.14.dist-info/entry_points.txt
cnspy_ranging_evaluation-0.2.14.dist-info/top_level.txt
cnspy_ranging_evaluation-0.2.14.dist-info/RECORD
